[
  {
    "KorisnickoIme": "IgorJ",
    "Lozinka": "123",
    "Ime": "Igor",
    "Prezime": "Janicevic",
    "Email": "igorjanicevic1@example.com",
    "DatumRodjenja": "2002-06-18",
    "Pol": 0,
    "TipKorisnika": 0,
    "ListaRezervacija": [ 1, 543 ]
  },
  {
    "KorisnickoIme": "ana_89",
    "Lozinka": "ana123!",
    "Ime": "Ana",
    "Prezime": "Anić",
    "Email": "ana.anic@example.com",
    "DatumRodjenja": "1989-12-28",
    "Pol": 1,
    "TipKorisnika": 1,
    "ListaRezervacija": []
  },
  {
    "KorisnickoIme": "Ivan Jan",
    "Lozinka": "ivan",
    "Ime": "Ivan",
    "Prezime": "Janicevic",
    "Email": "milkomilkic@yahoo.com",
    "DatumRodjenja": "2003-03-11",
    "Pol": 0,
    "TipKorisnika": 0,
    "ListaRezervacija": []
  }
]